MANIFEST.in
README.rst
setup.py
awsdatapipe/__init__.py
awsdatapipe/aws-datapipe
awsdatapipe/data/exportdynamo2s3.json