Metadata-Version: 1.1
Name: aws-datapipe
Version: 0.1.3
Summary: Tool for creating AWS data pipeline to export data from any DynamoDB table to an S3 bucket
Home-page: https://github.com/tmxak/aws-datapipe
Author: Maxim Tacu
Author-email: maxtacu95@gmail.com
License: MIT
Platform: UNKNOWN
Classifier: Programming Language :: Python :: 3.6
Classifier: License :: OSI Approved :: MIT License
Classifier: Topic :: System :: Systems Administration
Classifier: Intended Audience :: System Administrators
